zgcli/__init__.py
zgcli/__version__.py
zgcli/config.py
zgcli/main.py
zgcli/commands/__init__.py
zgcli/commands/status.py
zeroguard_cli-0.0.1.dev3.dist-info/LICENSE
zeroguard_cli-0.0.1.dev3.dist-info/METADATA
zeroguard_cli-0.0.1.dev3.dist-info/WHEEL
zeroguard_cli-0.0.1.dev3.dist-info/entry_points.txt
zeroguard_cli-0.0.1.dev3.dist-info/top_level.txt
zeroguard_cli-0.0.1.dev3.dist-info/RECORD
