Metadata-Version: 2.1
Name: zeroguard-cli
Version: 0.0.1.dev3
Summary: ZeroGuard CLI
Home-page: https://zeroguard.com
Author: ZeroGuard
Author-email: oss@zeroguard.com
License: AGPL-3.0
Project-URL: Documentation, https://zeroguard-cli.readthedocs.io
Project-URL: Source, https://github.com/zeroguard/zeroguard-cli
Platform: UNKNOWN
Classifier: Development Status :: 1 - Planning
Classifier: Environment :: Console
Classifier: Intended Audience :: Information Technology
Classifier: License :: OSI Approved :: GNU Affero General Public License v3
Classifier: Natural Language :: English
Classifier: Programming Language :: Python :: 3.5
Classifier: Programming Language :: Python :: 3.6
Classifier: Programming Language :: Python :: 3.7
Classifier: Programming Language :: Python :: 3.8
Classifier: Topic :: Security
Requires-Python: >=3.5
Requires-Dist: click (==7.0)
Requires-Dist: python-box (==3.4.6)
Requires-Dist: pyyaml (==5.2)
